Workbook

Sheet 0. Resumen
A1: El turno de la madrugada
A2: Turno de madrugada: cronica hipertextual y episodio de audio
A4: Autoria | B4: Leidy Carolina Granados Celis: investigacion, cronica, guion y voz
B5: Alexis Triana Quintana: desarrollo tecnico y construccion del sitio web
A6: Asignatura | B6: Taller de Creación de Contenidos - 53305
A7: Institucion | B7: Corporación Unificada Nacional de Educación Superior (CUN)
A8: Ciudad | B8: Santa Marta, Magdalena
A9: Periodo de ejecucion | B9: Septiembre de 2026
A10: Cronica web | B10: El turno de la madrugada, con cinco capas de contexto
A11: Episodio de audio | B11: "Lo que queda del dia", relato en primera persona
A13: Cifras de control
A14: Inversion CAPEX | B14: ='1. Presupuesto'!G11 -> 640000
A15: Inversion OPEX | B15: ='1. Presupuesto'!G22 -> 478000
A16: Inversion total | B16: ='1. Presupuesto'!G24 -> 1118000
A17: Duracion del proyecto (dias) | B17: ='2. Cronograma'!E17-'2. Cronograma'!D5+1 -> 20
A18: Valor de impacto (puntos) | B18: ='3. KPI e IEC'!E29 -> 5075
A19: Indice de Eficiencia de Contenido | B19: ='3. KPI e IEC'!E33 -> 4.539356
A21: Las cifras de este cuadro estan enlazadas a las hojas 1, 2 y 3: al cambiar un dato alli, aqui se actualiza solo.
A23: Los precios son estimaciones de mercado de septiembre de 2026 y se confirman contra la factura antes de ejecutar la compra.
A25: El desarrollo del sitio y la produccion sonora los hizo el equipo, por eso no aparecen como costo. Contratados por fuera, habria que sumar honorarios de desarrollo y de postproduccion.

Sheet 1. Presupuesto
A1: Presupuesto operativo
A2: El turno de la madrugada. Septiembre de 2026. Cifras en pesos colombianos
A3: Precios de mercado consultados en Santa Marta en septiembre de 2026. Se confirman contra factura antes de comprar.
A5: Tipo | B5: Categoria | C5: Concepto | D5: Cantidad | E5: Unidad | F5: Valor unitario | G5: Subtotal | H5: Justificacion
A6: CAPEX | B6: Captura de audio | C6: Micrófono de solapa con cable TRRS | D6: 1 | E6: unidad | F6: 180000 | G6: =D6*F6 -> 180000 | H6: Necesario para el estándar de -12 dB a -6 dB
A7: CAPEX | B7: Captura de audio | C7: Auriculares cerrados de monitoreo | D7: 1 | E7: unidad | F7: 150000 | G7: =D7*F7 -> 150000 | H7: Control de saturación durante la grabación
A8: CAPEX | B8: Captura de video | C8: Tripode con soporte para movil | D8: 1 | E8: unidad | F8: 90000 | G8: =D8*F8 -> 90000 | H8: Encuadre estable, regla de los tercios
A9: CAPEX | B9: Almacenamiento | C9: Tarjeta microSD 128 GB clase 10 | D9: 1 | E9: unidad | F9: 70000 | G9: =D9*F9 -> 70000 | H9: Brutos de audio y respaldo
A10: CAPEX | B10: Equipo base | C10: Movil 1080p: depreciacion del periodo | D10: 2 | E10: mes | F10: 75000 | G10: =D10*F10 -> 150000 | H10: Equipo propio de 1.800.000 a 24 meses
A11: Subtotal CAPEX: bienes duraderos y equipos | G11: =SUM(G6:G10) -> 640000
A13: OPEX | B13: Conectividad | C13: Plan de datos moviles | D13: 2 | E13: mes | F13: 60000 | G13: =D13*F13 -> 120000 | H13: Reporteria en terreno y publicacion
A14: OPEX | B14: Conectividad | C14: Internet fijo del hogar | D14: 2 | E14: mes | F14: 85000 | G14: =D14*F14 -> 170000 | H14: Edicion y desarrollo en franja de madrugada
A15: OPEX | B15: Transporte de campo | C15: Pasajes urbanos para reporteria | D15: 20 | E15: viaje | F15: 2900 | G15: =D15*F15 -> 58000 | H15: Centros de Escucha y recorridos por barrios
A16: OPEX | B16: Viaticos | C16: Alimentacion en jornadas de terreno | D16: 6 | E16: jornada | F16: 15000 | G16: =D16*F16 -> 90000 | H16: Salidas de mas de cinco horas
A17: OPEX | B17: Tramites | C17: Impresiones y papeleria del proyecto | D17: 1 | E17: global | F17: 25000 | G17: =D17*F17 -> 25000 | H17: Soportes fisicos del proceso de verificacion
A18: OPEX | B18: Publicacion | C18: Dominio propio: prorrateo del periodo | D18: 2 | E18: mes | F18: 7500 | G18: =D18*F18 -> 15000 | H18: Anualidad de 90.000 repartida
A19: OPEX | B19: Publicacion | C19: Alojamiento web y base de datos | D19: 2 | E19: mes | F19: 0 | G19: =D19*F19 -> 0 | H19: Vercel y Supabase en plan gratuito
A20: OPEX | B20: Publicacion | C20: Entrega del audio desde el propio sitio | D20: 2 | E20: mes | F20: 0 | G20: =D20*F20 -> 0 | H20: Archivo alojado en Vercel, sin costo adicional
A21: OPEX | B21: Postproduccion | C21: Software de edicion de audio | D21: 1 | E21: global | F21: 0 | G21: =D21*F21 -> 0 | H21: Audacity, software libre
A22: Subtotal OPEX: operacion, conectividad y trabajo de campo | G22: =SUM(G13:G21) -> 478000
A24: INVERSION TOTAL DEL PROYECTO | G24: =G11+G22 -> 1118000
A26: Peso de cada tipo
A27: CAPEX | B27: =G11/G24 -> 0.57245081
A28: OPEX | B28: =G22/G24 -> 0.42754919

Sheet 2. Cronograma
A1: Cronograma de tiempos y movimientos
A2: El turno de la madrugada. Diagrama de Gantt por fase y por pieza
G3: sep
A4: Fase | B4: Tarea | C4: Pieza | D4: Inicio | E4: Fin | F4: Dias | G4: 1 | H4: 2 | I4: 3 | J4: 4 | K4: 5 | L4: 6 | M4: 7 | N4: 8 | O4: 9 | P4: 10 | Q4: 11 | R4: 12 | S4: 13 | T4: 14 | U4: 15 | V4: 16 | W4: 17 | X4: 18 | Y4: 19 | Z4: 20
A5: Preproduccion intelectual | B5: Definicion del angulo y de la tesis | C5: Las dos | D5: 46266 | E5: 46267 | F5: =E5-D5+1 -> 2
B6: Rastreo documental: DANE, Minsalud, leyes | C6: Las dos | D6: 46267 | E6: 46270 | F6: =E6-D6+1 -> 4
B7: Verificacion factica de cada cifra | C7: Las dos | D7: 46269 | E7: 46273 | F7: =E7-D7+1 -> 5
B8: Consulta de la oferta institucional de bienestar | C8: Las dos | D8: 46272 | E8: 46273 | F8: =E8-D8+1 -> 2
A9: Produccion de la cronica | B9: Escritura de la cronica | C9: Cronica | D9: 46270 | E9: 46274 | F9: =E9-D9+1 -> 5
B10: Diseno de las cinco capas del hipertexto | C10: Cronica | D10: 46273 | E10: 46275 | F10: =E10-D10+1 -> 3
A11: Produccion del audio | B11: Guion del episodio en primera persona | C11: Audio | D11: 46274 | E11: 46275 | F11: =E11-D11+1 -> 2
B12: Grabacion en franja de madrugada | C12: Audio | D12: 46276 | E12: 46277 | F12: =E12-D12+1 -> 2
A13: Postproduccion | B13: Desarrollo y accesibilidad del sitio | C13: Cronica | D13: 46274 | E13: 46278 | F13: =E13-D13+1 -> 5
B14: Edicion y control de niveles del audio | C14: Audio | D14: 46277 | E14: 46278 | F14: =E14-D14+1 -> 2
B15: Publicacion de las dos piezas | C15: Las dos | D15: 46278 | E15: 46278 | F15: =E15-D15+1 -> 1
A16: Distribucion y medicion | B16: Difusion y recogida de aportes del publico | C16: Las dos | D16: 46278 | E16: 46285 | F16: =E16-D16+1 -> 8
B17: Lectura de metricas y calculo del IEC | C17: Las dos | D17: 46283 | E17: 46285 | F17: =E17-D17+1 -> 3
A19: Leyenda
B20: Preproduccion intelectual
B21: Produccion de la cronica
B22: Produccion del audio
B23: Postproduccion
B24: Distribucion y medicion

Sheet 3. KPI e IEC
A1: Tablero de control de impacto
A2: El turno de la madrugada. Proyeccion de alcance, engagement y conversion a 30 dias de la publicacion
A3: La columna de la derecha es el resultado que se espera alcanzar, no una medicion: las piezas se publican el 13 de septiembre y las metricas se leen entre el 18 y el 20.
A5: Dimension | B5: Indicador | C5: Meta | D5: Proyeccion | E5: Cumplimiento | F5: Fuente de medicion
A6: Alcance | B6: Visitas unicas a la cronica | C6: 400 | D6: 312 | E6: =IFERROR(D6/C6,0) -> 0.78 | F6: Vercel Analytics
B7: Reproducciones iniciadas del episodio en el sitio | C7: 150 | D7: 118 | E7: =IFERROR(D7/C7,0) -> 0.78666667 | F7: Analitica del sitio
B8: Impresiones en difusion directa | C8: 600 | D8: 540 | E8: =IFERROR(D8/C8,0) -> 0.9 | F8: WhatsApp e Instagram
B9: Total Alcance | C9: =SUM(C6:C8) -> 1150 | D9: =SUM(D6:D8) -> 970 | E9: =IFERROR(D9/C9,0) -> 0.84347826
A11: Engagement | B11: Capas del hipertexto abiertas | C11: 300 | D11: 268 | E11: =IFERROR(D11/C11,0) -> 0.89333333 | F11: Evento en el sitio
B12: Votos en la encuesta | C12: 120 | D12: 94 | E12: =IFERROR(D12/C12,0) -> 0.78333333 | F12: Base de datos del sitio
B13: Escucha superior al 50 % del episodio | C13: 90 | D13: 71 | E13: =IFERROR(D13/C13,0) -> 0.78888889 | F13: Analitica del sitio
B14: Total Engagement | C14: =SUM(C11:C13) -> 510 | D14: =SUM(D11:D13) -> 433 | E14: =IFERROR(D14/C14,0) -> 0.84901961
A16: Conversion | B16: Aportes escritos en el muro | C16: 40 | D16: 31 | E16: =IFERROR(D16/C16,0) -> 0.775 | F16: Base de datos del sitio
B17: Clics en las lineas de ayuda | C17: 25 | D17: 19 | E17: =IFERROR(D17/C17,0) -> 0.76 | F17: Evento en el sitio
B18: Episodio escuchado hasta el final | C18: 60 | D18: 47 | E18: =IFERROR(D18/C18,0) -> 0.78333333 | F18: Analitica del sitio
B19: Total Conversion | C19: =SUM(C16:C18) -> 125 | D19: =SUM(D16:D18) -> 97 | E19: =IFERROR(D19/C19,0) -> 0.776
A22: Indice de Eficiencia de Contenido (IEC)
A23: Convierte el impacto conseguido en puntos y lo divide entre la inversion. Una conversion pesa mas que una impresion: quien escribe su turno o marca una linea de ayuda hizo algo, no solo paso por delante.
A25: Dimension | B25: Formula | C25: Resultado | D25: Peso | E25: Puntos de impacto | F25: Nota
A26: Alcance | B26: Total logrado en Alcance | C26: =D9 -> 970 | D26: 1 | E26: =C26*D26 -> 970 | F26: Contacto con la pieza
A27: Engagement | B27: Total logrado en Engagement | C27: =D14 -> 433 | D27: 5 | E27: =C27*D27 -> 2165 | F27: Interaccion con la pieza
A28: Conversion | B28: Total logrado en Conversion | C28: =D19 -> 97 | D28: 20 | E28: =C28*D28 -> 1940 | F28: Accion completada por el publico
B29: Valor de impacto total (puntos) | E29: =SUM(E26:E28) -> 5075
B31: Inversion total del proyecto | E31: ='1. Presupuesto'!G24 -> 1118000 | F31: Enlazado con la hoja 1
A33: IEC = Valor de impacto / Inversion total x 1.000 | E33: =IFERROR(E29/E31*1000,0) -> 4.539356 | F33: puntos por cada 1.000 COP
A35: Lectura del indice: cada 1.000 pesos invertidos produjeron esa cantidad de puntos de impacto. Sirve para comparar entre piezas y entre periodos, no como cifra absoluta.
